{"type":"FeatureCollection","features":[{"geometry":{"coordinates":[4.83050286769867,45.771981453653225],"type":"Point"},"properties":{"author":"graphull_____","authorid":"7001793922","caption":"Par @cap_phi #streetart #streetartlyon #streetartcroixrousse #artderue #arturbain #urbanart #interditdinterdire #panneaux #sensinterdit #capphi #monstres","imageURL":"https://scontent-cdg2-1.cdninstagram.com/vp/25d1f86410be13248e347739ba75f4af/5BA49A1E/t51.2885-15/s640x640/sh0.08/e35/33095235_1923965147894756_4145368448299433984_n.jpg","insta_infos":{"author":"graphull_____","authorid":"7001793922","id":"1796277466714988198","imageURL":"https://scontent-cdg2-1.cdninstagram.com/vp/82810da9ecc962290a4c4e7792f30716/5BA7A434/t51.2885-15/e35/33095235_1923965147894756_4145368448299433984_n.jpg","location":{"has_public_page":true,"id":"235077454","name":"Pentes de la Croix-Rousse","slug":"pentes-de-la-croix-rousse"},"timestamp":1528352982},"instagramcode":"BjtqNbBld6m","instagramid":"1796277466714988198","mustbepublished":false,"originURL":"https://scontent-cdg2-1.cdninstagram.com/vp/82810da9ecc962290a4c4e7792f30716/5BA7A434/t51.2885-15/e35/33095235_1923965147894756_4145368448299433984_n.jpg","originally_localized":true,"post_date":"2018-06-07 08:29:42","timestamp":1528352982,"validated":true},"type":"Feature"}]}